README.rst
setup.py
wmon/__init__.py
wmon/wmon.py
wmon/wmonpy2.py
wmon/wmonpy3.py
wmon.egg-info/PKG-INFO
wmon.egg-info/SOURCES.txt
wmon.egg-info/dependency_links.txt
wmon.egg-info/entry_points.txt
wmon.egg-info/requires.txt
wmon.egg-info/top_level.txt