Metadata-Version: 1.1
Name: wmon
Version: 0.63
Summary: This Script return a plain text report with a complete system info.
Home-page: https://github.com/pcpractico/Wmon
Author: Francisco Martinez
Author-email: fmartinez@pcpractico.es
License: BSD
Keywords: monitoring system
Platform: UNKNOWN
Classifier: Development Status :: 2 - Pre-Alpha
Classifier: Programming Language :: Python :: 3.0
Classifier: Programming Language :: Python :: 3.1
Classifier: Programming Language :: Python :: 3.2
Classifier: Programming Language :: Python :: 3.3
Classifier: Programming Language :: Python :: 3.4
Classifier: Topic :: Utilities
Classifier: Topic :: System :: Monitoring
Classifier: Topic :: System :: Networking :: Monitoring
Classifier: Natural Language :: English
Classifier: License :: OSI Approved :: BSD License
Classifier: Operating System :: POSIX :: Linux
Classifier: Operating System :: Microsoft
Classifier: Operating System :: Microsoft :: Windows :: Windows NT/2000
